{"id":"KLRV24RKKA7WT","name":"img-1602155956010_logo","size":299379,"btime":1614680465658,"mtime":1614680466150,"ext":"jpg","tags":[],"folders":["KNYAM0L9LOAUX"],"isDeleted":false,"url":"","annotation":"","modificationTime":1614680466161,"height":1249,"width":2000,"lastModified":1620373108404,"palettes":[{"color":[135,128,117],"ratio":56},{"color":[181,174,161],"ratio":12},{"color":[92,86,79],"ratio":10},{"color":[40,36,31],"ratio":9},{"color":[215,215,204],"ratio":7},{"color":[113,101,82],"ratio":1.69},{"color":[110,90,76],"ratio":0.74},{"color":[83,72,50],"ratio":0.35}]}