{"id":"KLJ4YIF4DZY0Q","name":"tree-house-aibek-almassov-forest-architecture_dezeen_1568_1","size":726428,"btime":1614152897803,"mtime":1614152898713,"ext":"jpg","tags":[],"folders":["KNYAM0L9LOAUX"],"isDeleted":false,"url":"","annotation":"","modificationTime":1614152898725,"height":1120,"width":1568,"lastModified":1620373105300,"palettes":[{"color":[21,33,32],"ratio":63},{"color":[175,180,181],"ratio":12},{"color":[122,163,187],"ratio":8},{"color":[106,104,81],"ratio":6},{"color":[55,73,54],"ratio":3.62},{"color":[62,97,95],"ratio":1.53},{"color":[95,125,149],"ratio":1.11},{"color":[54,77,94],"ratio":1.05},{"color":[162,127,77],"ratio":0.92}]}