{"id":"KKCF2S0QISQU1","name":"ansel-hsiao-bellator94","size":169077,"btime":1611569847410,"mtime":1611569847411,"ext":"jpg","tags":[],"folders":["KKCFEEA4UU04O"],"isDeleted":false,"url":"","annotation":"","modificationTime":1611569847414,"height":1200,"width":1920,"orientation":1,"palettes":[{"color":[4,4,4],"ratio":88,"$$hashKey":"object:1337"},{"color":[137,146,152],"ratio":4.95,"$$hashKey":"object:1338"},{"color":[74,82,87],"ratio":3.48,"$$hashKey":"object:1339"},{"color":[40,45,48],"ratio":0.85,"$$hashKey":"object:1340"},{"color":[99,109,115],"ratio":0.72,"$$hashKey":"object:1341"},{"color":[89,98,108],"ratio":0.69,"$$hashKey":"object:1342"},{"color":[51,60,65],"ratio":0.53,"$$hashKey":"object:1343"},{"color":[46,52,60],"ratio":0.38,"$$hashKey":"object:1344"}],"lastModified":1611570403429}