{"id":"KLLX47NO50G3P","name":"nano-giga-interactive-astronomer-room-keyart","size":377774,"btime":1614321124992,"mtime":1614321124992,"ext":"jpg","tags":[],"folders":["KNYAM0L9LOAUX"],"isDeleted":false,"url":"","annotation":"","modificationTime":1614321124996,"height":926,"width":1920,"lastModified":1620373108410,"palettes":[{"color":[11,18,16],"ratio":45},{"color":[26,48,43],"ratio":15},{"color":[38,72,66],"ratio":11},{"color":[29,58,63],"ratio":6},{"color":[71,110,108],"ratio":5},{"color":[59,51,31],"ratio":5},{"color":[56,86,97],"ratio":4.22},{"color":[97,75,45],"ratio":2.81},{"color":[184,170,106],"ratio":1.11},{"color":[84,173,150],"ratio":1.03},{"color":[69,139,158],"ratio":0.85}]}