{"id":"KMERQJU9MSKAZ","name":"hue-teo-the-houses-in-the-valley","size":488981,"btime":1616065610191,"mtime":1616065610192,"ext":"jpg","tags":[],"folders":["KNYAM0L9LOAUX"],"isDeleted":false,"url":"","annotation":"","modificationTime":1616065610195,"height":711,"width":1920,"lastModified":1620373113044,"palettes":[{"color":[34,64,45],"ratio":34},{"color":[94,154,213],"ratio":22},{"color":[54,117,139],"ratio":10},{"color":[200,229,238],"ratio":9},{"color":[118,117,67],"ratio":5},{"color":[44,94,92],"ratio":5},{"color":[74,135,81],"ratio":3.84},{"color":[35,107,193],"ratio":3.4},{"color":[121,186,102],"ratio":3.24},{"color":[192,153,76],"ratio":2.42}]}