{"id":"KNPO2V4SBMH1W","name":"2747c40012f5b887c9a0b3cb9db5c47b","size":72229,"btime":1618901374494,"mtime":1618901375341,"ext":"jpg","tags":[],"folders":["KNYAM0L9LOAUX"],"isDeleted":false,"url":"","annotation":"","modificationTime":1618901375345,"noThumbnail":true,"width":564,"height":564,"lastModified":1619428337924,"palettes":[{"color":[101,136,208],"ratio":47,"$$hashKey":"object:6518"},{"color":[86,102,54],"ratio":18,"$$hashKey":"object:6519"},{"color":[225,223,219],"ratio":17,"$$hashKey":"object:6520"},{"color":[98,107,132],"ratio":8,"$$hashKey":"object:6521"},{"color":[158,172,203],"ratio":5,"$$hashKey":"object:6522"},{"color":[166,210,238],"ratio":2.22,"$$hashKey":"object:6523"},{"color":[37,92,121],"ratio":0.42,"$$hashKey":"object:6524"}]}