{"id":"KLDFMRVCT6YML","name":"randall-mackey-orkaan-building-sketches-01","size":225938,"btime":1613808028630,"mtime":1613808028630,"ext":"jpg","tags":[],"folders":["KNYAM0L9LOAUX"],"isDeleted":false,"url":"","annotation":"","modificationTime":1613808028635,"noThumbnail":true,"width":1400,"height":829,"lastModified":1620373105317,"palettes":[{"color":[227,227,227],"ratio":62,"$$hashKey":"object:4552"},{"color":[70,71,71],"ratio":22,"$$hashKey":"object:4553"},{"color":[139,139,139],"ratio":9,"$$hashKey":"object:4554"},{"color":[185,185,185],"ratio":3.57,"$$hashKey":"object:4555"},{"color":[108,107,107],"ratio":1.5,"$$hashKey":"object:4556"}]}